odoo/addons/sale_blanket_order_cancel_state/LICENSE
odoo/addons/sale_blanket_order_cancel_state/README.rst
odoo/addons/sale_blanket_order_cancel_state/__init__.py
odoo/addons/sale_blanket_order_cancel_state/__manifest__.py
odoo/addons/sale_blanket_order_cancel_state/images/screen.png
odoo/addons/sale_blanket_order_cancel_state/models/__init__.py
odoo/addons/sale_blanket_order_cancel_state/models/blanket_order.py
odoo/addons/sale_blanket_order_cancel_state/static/description/icon.png
odoo/addons/sale_blanket_order_cancel_state/static/description/index.html
odoo/addons/sale_blanket_order_cancel_state/tests/TEST_INSTRUCTIONS.rst
odoo/addons/sale_blanket_order_cancel_state/views/view_blanket_order_form.xml
odoo_addon_sale_blanket_order_cancel_state-16.0.1.0.0.dist-info/METADATA
odoo_addon_sale_blanket_order_cancel_state-16.0.1.0.0.dist-info/WHEEL
odoo_addon_sale_blanket_order_cancel_state-16.0.1.0.0.dist-info/top_level.txt
odoo_addon_sale_blanket_order_cancel_state-16.0.1.0.0.dist-info/RECORD
